brainfuck_art/__init__.py
brainfuck_art/__main__.py
brainfuck_art/__version__.py
brainfuck_art/brainfuck_generation.py
brainfuck_art/brainfuck_interpreter.py
brainfuck_art/color_utils.py
brainfuck_art/image_processing.py
brainfuck_art/output_html.py
brainfuck_art/output_pdf.py
brainfuck_art/output_svg.py
brainfuck_art-1.0.1.dist-info/LICENSE
brainfuck_art-1.0.1.dist-info/METADATA
brainfuck_art-1.0.1.dist-info/WHEEL
brainfuck_art-1.0.1.dist-info/entry_points.txt
brainfuck_art-1.0.1.dist-info/top_level.txt
brainfuck_art-1.0.1.dist-info/RECORD
