Metadata-Version: 2.1
Name: brainfuck_art
Version: 1.0.1
Summary: A Python library to generate Brainfuck code, convert images to ASCII art, and create PDFs or HTML outputs.
Author-email: Pablo Marcos-Manchón <pmarcos@ub.edu>
License: MIT
Project-URL: repository, https://github.com/pablomm/brainfuck-art/
Keywords: brainfuck,ASCII art,image processing,PDF generation,HTML generation,programming languages
Classifier: Development Status :: 4 - Beta
Classifier: Intended Audience :: Developers
Classifier: Intended Audience :: Education
Classifier: License :: OSI Approved :: MIT License
Classifier: Natural Language :: English
Classifier: Operating System :: OS Independent
Classifier: Programming Language :: Python :: 3.9
Classifier: Programming Language :: Python :: 3.10
Classifier: Programming Language :: Python :: 3.11
Classifier: Programming Language :: Python :: 3.12
Classifier: Topic :: Text Processing
Classifier: Topic :: Multimedia :: Graphics
Requires-Python: >=3.9
License-File: LICENSE
Requires-Dist: Pillow
Requires-Dist: numpy
Requires-Dist: svglib
Requires-Dist: reportlab
Provides-Extra: docs
Requires-Dist: sphinx; extra == "docs"
Requires-Dist: pydata-sphinx-theme; extra == "docs"
